<PAMDataset>
  <Metadata />
  <Metadata domain="Esri">
    <MDI key="PyramidResamplingType">NEAREST</MDI>
  </Metadata>
  <PAMRasterBand band="1">
    <Histograms>
      <HistItem>
        <HistMin>-0.5</HistMin>
        <HistMax>789.5</HistMax>
        <BucketCount>790</BucketCount>
        <IncludeOutOfRange>1</IncludeOutOfRange>
        <Approximate>0</Approximate>
        <HistCounts>295|199|237|30|438|280|440|216|71|514|165|351|314|275|53|41|427|264|95|70|27|344|100|10|17|146|126|56|109|78|76|250|146|210|84|241|192|418|270|109|224|135|710|72|136|84|312|11|20|81|26|64|250|207|129|21|125|96|122|132|102|78|1032|67|104|427|29|131|415|456|357|404|448|365|310|339|31|64|361|62|348|68|125|218|199|103|35|131|48|64|65|231|225|64|84|129|124|72|120|306|40|432|43|218|51|104|337|44|37|368|63|870|489|282|106|884|485|319|35|154|69|144|380|225|170|166|373|209|362|108|117|492|105|101|108|104|117|199|119|32|40|39|133|50|206|128|154|160|173|302|196|357|202|225|136|551|86|79|88|6|440|106|27|87|40|346|162|80|65|146|44|217|237|193|119|132|198|190|11|129|115|70|278|10|15|9|15|78|62|247|239|65|199|599|339|223|257|259|151|158|88|500|298|63|178|34|73|103|10|19|188|108|247|386|34|111|188|58|273|747|300|70|98|74|59|155|70|99|307|121|40|194|130|43|6|17|10|51|105|11|44|229|40|217|348|63|122|72|45|127|346|2621|293|113|49|578|55|40|24|165|243|549|314|517|520|325|54|1056|14|758|713|44|38|145|41|49|626|202|512|107|210|86|287|34|140|297|106|596|21|54|573|93|214|231|530|116|102|9|133|21|446|19|631|22|364|655|134|183|74|144|304|659|77|98|574|185|184|112|277|123|129|60|222|20|213|178|79|9|133|64|54|84|102|68|35|9|199|49|14|126|726|538|59|50|112|114|206|103|108|216|186|69|17|153|142|29|189|58|151|57|195|325|195|270|99|145|83|203|182|120|56|40|43|29|46|17|26|19|88|20|16|378|429|106|779|1833|1835|781|281|22|81|21|41|41|55|51|20|80|5|285|58|56|57|90|84|75|40|28|26|30|32|33|37|26|312|52|18|28|39|19|41|29|146|699|566|227|186|32|105|629|119|627|117|104|71|76|203|252|20|87|24|43|76|175|7|17|54|3|20|17|96|105|87|30|17|8|281|34|19|36|18|50|32|149|20|27|30|38|79|86|162|124|163|51|63|71|91|22|19|158|76|183|18|49|78|93|90|164|244|218|57|107|184|157|198|211|167|19|11|6|24|13|13|12|11|19|33|21|25|36|21|60|699|39|79|94|125|110|9|105|155|183|156|17|20|107|20|54|55|33|33|130|396|83|39|40|26|67|39|74|20|25|71|64|64|40|38|38|7|8|8|26|108|7|20|128|8|20|49|50|15|164|101|36|461|10|29|32|270|210|99|20|10|17|52|6|8|71|9|35|46|21|73|91|76|196|161|192|135|254|67|5|25|22|15|14|49|15|67|105|119|160|183|206|270|118|62|25|6|25|286|10|31|80|9|12|18|105|14|17|254|23|547|282|40|73|89|17|16|37|83|31|139|249|30|31|183|12|6|9|12|39|39|11|73|11|44|9|50|4|36|22|7|39|39|39|29|5|7|24|7|15|8|7|2|780|72|256|22|59|53|27|106|9|8|16|117|10|52|34|17|219|5|6|177|5|208|621|823|487|490|57|110|54|58|43|193|14|16|66|1|42|29|2|30|58|22|86|38|27|26|703|122|71|173|546|274|63|89|269|223|108|704|107|99|311|10|6|80|9|25|27|60|6|491|12|75|13|14|162|43|18|10|38|65|54|121|836|67|50|8|23|44|26|15|19|18|118|81|7|26|29|11|66|32|17|21|42|39|514|307|788|219|38|209|204|30|40|42|34|13|9|10|103|99|72|101|14|344|54</HistCounts>
      </HistItem>
    </Histograms>
    <Metadata>
      <MDI key="RepresentationType">THEMATIC</MDI>
      <MDI key="STATISTICS_MINIMUM">0</MDI>
      <MDI key="STATISTICS_MAXIMUM">789</MDI>
      <MDI key="STATISTICS_MEAN">331.77424079846</MDI>
      <MDI key="STATISTICS_STDDEV">220.29014364866</MDI>
      <MDI key="STATISTICS_SKIPFACTORX">1</MDI>
      <MDI key="STATISTICS_SKIPFACTORY">1</MDI>
      <MDI key="STATISTICS_COVARIANCES">48527.7473887466</MDI>
    </Metadata>
  </PAMRasterBand>
</PAMDataset>
